adup/__init__.py
adup/backends.py
adup/cli.py
adup/exceptions.py
adup/logging.py
adup/utils.py
adup/commands/__init__.py
adup/commands/analyze.py
adup/commands/cp.py
adup/commands/init.py
adup/commands/initdb.py
adup/commands/list.py
adup/commands/mark.py
adup/commands/mv.py
adup/commands/rm.py
adup/commands/show.py
adup/commands/updatedb.py
adup-0.1.0.dist-info/LICENSE
adup-0.1.0.dist-info/METADATA
adup-0.1.0.dist-info/WHEEL
adup-0.1.0.dist-info/entry_points.txt
adup-0.1.0.dist-info/top_level.txt
adup-0.1.0.dist-info/RECORD
